ckanext/__init__.py
ckanext/cloudstorage_api/__init__.py
ckanext/cloudstorage_api/__version__.py
ckanext/cloudstorage_api/auth.py
ckanext/cloudstorage_api/blueprints.py
ckanext/cloudstorage_api/cli.py
ckanext/cloudstorage_api/logic.py
ckanext/cloudstorage_api/models.py
ckanext/cloudstorage_api/plugin.py
ckanext/cloudstorage_api/storage.py
ckanext_cloudstorage_api-0.2.0.dist-info/entry_points.txt
ckanext_cloudstorage_api-0.2.0.dist-info/WHEEL
ckanext_cloudstorage_api-0.2.0.dist-info/METADATA
ckanext_cloudstorage_api-0.2.0.dist-info/licenses/LICENSE
ckanext_cloudstorage_api-0.2.0.dist-info/RECORD
