Metadata-Version: 2.1
Name: ckanext-cloudstorage_api
Version: 0.2.0
Summary: Extension to manage CKAN resources in any S3-like object storage.
License: MIT
Keywords: CKAN,cloudstorage,s3,bucket,cloud
Author-email: Sam Woodcock <sam.woodcock@protonmail.com>
Requires-Python: >=3.8
Classifier: Programming Language :: Python
Classifier: Programming Language :: Python :: 3 :: Only
Classifier: Programming Language :: Python :: 3.10
Classifier: Programming Language :: Python :: 3.8
Classifier: Programming Language :: Python :: 3.9
Classifier: Topic :: Utilities
Requires-Dist: apache-libcloud>=3.8.0
Requires-Dist: boto3>=1.26.135
Project-URL: documentation, https://envidat.gitlab-pages.wsl.ch/ckanext-cloudstorage_api
Project-URL: homepage, https://gitlabext.wsl.ch/EnviDat/ckanext-cloudstorage_api.git
Project-URL: repository, https://gitlabext.wsl.ch/EnviDat/ckanext-cloudstorage_api.git
